{
  "indexes": [
    {
      "collectionGroup": "import_jobs",
      "queryScope": "COLLECTION",
      "fields": [
        { "fieldPath": "triggeredBy", "order": "ASCENDING" },
        { "fieldPath": "startedAt", "order": "DESCENDING" }
      ]
    },
    {
      "collectionGroup": "leads",
      "queryScope": "COLLECTION",
      "fields": [
        { "fieldPath": "importBatchId", "order": "ASCENDING" },
        { "fieldPath": "createdAt", "order": "DESCENDING" }
      ]
    },
    {
      "collectionGroup": "commission_records",
      "queryScope": "COLLECTION",
      "fields": [
        { "fieldPath": "rmOwnerId", "order": "ASCENDING" },
        { "fieldPath": "createdAt", "order": "DESCENDING" }
      ]
    },
    {
      "collectionGroup": "commission_records",
      "queryScope": "COLLECTION",
      "fields": [
        { "fieldPath": "status", "order": "ASCENDING" },
        { "fieldPath": "createdAt", "order": "DESCENDING" }
      ]
    },
    {
      "collectionGroup": "leads",
      "queryScope": "COLLECTION",
      "fields": [
        { "fieldPath": "deleted", "order": "ASCENDING" },
        { "fieldPath": "createdAt", "order": "DESCENDING" }
      ]
    },
    {
      "collectionGroup": "leads",
      "queryScope": "COLLECTION",
      "fields": [
        { "fieldPath": "primaryOwnerId", "order": "ASCENDING" },
        { "fieldPath": "deleted", "order": "ASCENDING" },
        { "fieldPath": "createdAt", "order": "DESCENDING" }
      ]
    },
    {
      "collectionGroup": "leads",
      "queryScope": "COLLECTION",
      "fields": [
        { "fieldPath": "referredBy", "order": "ASCENDING" },
        { "fieldPath": "deleted", "order": "ASCENDING" },
        { "fieldPath": "createdAt", "order": "DESCENDING" }
      ]
    },
    {
      "collectionGroup": "announcements",
      "queryScope": "COLLECTION",
      "fields": [
        { "fieldPath": "isActive",    "order": "ASCENDING"  },
        { "fieldPath": "publishedAt", "order": "DESCENDING" }
      ]
    },
    {
      "collectionGroup": "activities",
      "queryScope": "COLLECTION_GROUP",
      "fields": [
        { "fieldPath": "by", "order": "ASCENDING"  },
        { "fieldPath": "at", "order": "DESCENDING" }
      ]
    },
    {
      "collectionGroup": "providers",
      "queryScope": "COLLECTION",
      "fields": [
        { "fieldPath": "type",   "order": "ASCENDING" },
        { "fieldPath": "active", "order": "ASCENDING" }
      ]
    },
    {
      "collectionGroup": "opportunity_types",
      "queryScope": "COLLECTION",
      "fields": [
        { "fieldPath": "businessLine", "order": "ASCENDING" },
        { "fieldPath": "active",       "order": "ASCENDING" }
      ]
    },
    {
      "collectionGroup": "access_logs",
      "queryScope": "COLLECTION",
      "fields": [
        { "fieldPath": "actorId",     "order": "ASCENDING" },
        { "fieldPath": "accessedAt",  "order": "DESCENDING" }
      ]
    },
    {
      "collectionGroup": "access_logs",
      "queryScope": "COLLECTION",
      "fields": [
        { "fieldPath": "targetId",    "order": "ASCENDING" },
        { "fieldPath": "accessedAt",  "order": "DESCENDING" }
      ]
    },
    {
      "collectionGroup": "attendance",
      "queryScope": "COLLECTION",
      "fields": [
        { "fieldPath": "userId", "order": "ASCENDING" },
        { "fieldPath": "date",   "order": "DESCENDING" }
      ]
    },
    {
      "collectionGroup": "attendance",
      "queryScope": "COLLECTION",
      "fields": [
        { "fieldPath": "date",   "order": "ASCENDING" },
        { "fieldPath": "status", "order": "ASCENDING" }
      ]
    },
    {
      "collectionGroup": "leave_applications",
      "queryScope": "COLLECTION",
      "fields": [
        { "fieldPath": "employeeId", "order": "ASCENDING" },
        { "fieldPath": "appliedAt",  "order": "DESCENDING" }
      ]
    },
    {
      "collectionGroup": "leave_applications",
      "queryScope": "COLLECTION",
      "fields": [
        { "fieldPath": "status",    "order": "ASCENDING" },
        { "fieldPath": "appliedAt", "order": "ASCENDING" }
      ]
    },
    {
      "collectionGroup": "payslips",
      "queryScope": "COLLECTION",
      "fields": [
        { "fieldPath": "employeeId", "order": "ASCENDING" },
        { "fieldPath": "month",      "order": "DESCENDING" }
      ]
    },
    {
      "collectionGroup": "holidays",
      "queryScope": "COLLECTION",
      "fields": [
        { "fieldPath": "year", "order": "ASCENDING" },
        { "fieldPath": "date", "order": "ASCENDING" }
      ]
    },
    {
      "collectionGroup": "commission_statements",
      "queryScope": "COLLECTION",
      "fields": [
        { "fieldPath": "providerId",  "order": "ASCENDING" },
        { "fieldPath": "periodStart", "order": "ASCENDING" }
      ]
    },
    {
      "collectionGroup": "lines",
      "queryScope": "COLLECTION_GROUP",
      "fields": [
        { "fieldPath": "statementId", "order": "ASCENDING" },
        { "fieldPath": "status",      "order": "ASCENDING" }
      ]
    },
    {
      "collectionGroup": "lines",
      "queryScope": "COLLECTION_GROUP",
      "fields": [
        { "fieldPath": "statementId", "order": "ASCENDING" },
        { "fieldPath": "parsedDate",  "order": "ASCENDING" }
      ]
    },
    {
      "collectionGroup": "rm_payouts",
      "queryScope": "COLLECTION",
      "fields": [
        { "fieldPath": "rmId",        "order": "ASCENDING" },
        { "fieldPath": "periodStart", "order": "DESCENDING" }
      ]
    },
    {
      "collectionGroup": "rm_payouts",
      "queryScope": "COLLECTION",
      "fields": [
        { "fieldPath": "status",      "order": "ASCENDING" },
        { "fieldPath": "periodStart", "order": "DESCENDING" }
      ]
    },
    {
      "collectionGroup": "opportunities",
      "queryScope": "COLLECTION_GROUP",
      "fields": [
        { "fieldPath": "ownerId",   "order": "ASCENDING" },
        { "fieldPath": "status",    "order": "ASCENDING" },
        { "fieldPath": "createdAt", "order": "DESCENDING" }
      ]
    },
    {
      "collectionGroup": "opportunities",
      "queryScope": "COLLECTION_GROUP",
      "fields": [
        { "fieldPath": "status",             "order": "ASCENDING" },
        { "fieldPath": "lostDetails.reason", "order": "ASCENDING" },
        { "fieldPath": "updatedAt",          "order": "DESCENDING" }
      ]
    },
    {
      "collectionGroup": "bank_submissions",
      "queryScope": "COLLECTION_GROUP",
      "fields": [
        { "fieldPath": "providerId",   "order": "ASCENDING" },
        { "fieldPath": "disbursedAt",  "order": "DESCENDING" },
        { "fieldPath": "interestRate", "order": "ASCENDING" }
      ]
    },
    {
      "collectionGroup": "opportunities",
      "queryScope": "COLLECTION_GROUP",
      "fields": [
        { "fieldPath": "primaryOwnerId", "order": "ASCENDING" },
        { "fieldPath": "source",         "order": "ASCENDING" },
        { "fieldPath": "createdAt",      "order": "DESCENDING" }
      ]
    }
  ],
  "fieldOverrides": []
}
